trop/placeholder.py
trop-0.1.0.dist-info/METADATA
trop-0.1.0.dist-info/WHEEL
trop-0.1.0.dist-info/RECORD
