Metadata-Version: 2.4
Name: trop
Version: 0.1.0
Summary: Package that implements the Triply Robust Panel Estimator (TROP)
License: MIT
Author: meganndare, zhaonanq
Requires-Python: >=3.9
Classifier: License :: OSI Approved :: MIT License
Classifier: Programming Language :: Python :: 3
Classifier: Programming Language :: Python :: 3.9
Classifier: Programming Language :: Python :: 3.10
Classifier: Programming Language :: Python :: 3.11
Classifier: Programming Language :: Python :: 3.12
Classifier: Programming Language :: Python :: 3.13
Classifier: Programming Language :: Python :: 3.14
Requires-Dist: cvxpy (==1.4.1)
Requires-Dist: joblib (==1.3.2)
Requires-Dist: numpy (==1.26.2)
Requires-Dist: pandas (==2.1.3)
